libjschoe/3dplot.py
libjschoe/__init__.py
libjschoe/_contour.py
libjschoe/contour.py
libjschoe/plot.py
libjschoe/test_.py
plot/3dplot.py
plot/contour.py
libjschoe-0.0.1.2.dist-info/METADATA
libjschoe-0.0.1.2.dist-info/WHEEL
libjschoe-0.0.1.2.dist-info/top_level.txt
libjschoe-0.0.1.2.dist-info/RECORD
