Metadata-Version: 2.1
Name: libjschoe
Version: 0.0.1.2
Summary: research library by jschoe
Author: jschoe
Author-email: jschoe71@gmail.com
License: MIT
Requires-Python: >=3
Requires-Dist: pandas
Requires-Dist: numpy
Requires-Dist: scipy
Requires-Dist: matplotlib >=3.3.0
